{
  "C:\\Program Files\\Java\\jre1.8.0_111\\lib\\ext\\jfxrt.jar": {
    "coordinate": "jre:jre:zip:call:1.0.0",
    "location": "C:\\Program Files\\Java\\jre1.8.0_111\\lib\\ext\\jfxrt.jar",
    "status": "RESOLVED",
    "error": "No class path info available for \u0027C:\\Program Files\\Java\\jre1.8.0_111\\lib\\ext\\jfxrt.jar\u0027. Skipped."
  },
  "C:\\Program Files\\Java\\jre1.8.0_111\\lib\\rt.jar": {
    "coordinate": "jre:jre:zip:call:1.0.0",
    "location": "C:\\Program Files\\Java\\jre1.8.0_111\\lib\\rt.jar",
    "status": "RESOLVED"
  },
  "C:\\Users\\Kyle\\git\\TeamCobraProject\\UndergroundHero\\src": {
    "location": "C:\\Users\\Kyle\\git\\TeamCobraProject\\UndergroundHero\\src",
    "status": "UNRESOLVED",
    "error": "No class path info available for \u0027C:\\Users\\Kyle\\git\\TeamCobraProject\\UndergroundHero\\src\u0027. Skipped."
  }
}